bakkes_rcon/__init__.py
bakkes_rcon/client.py
bakkes_rcon/enums.py
bakkes_rcon/exceptions.py
bakkes_rcon/inventory.py
bakkes_rcon/types.py
bakkes_rcon/util.py
bakkes_rcon-0.0.1.dist-info/LICENSE
bakkes_rcon-0.0.1.dist-info/WHEEL
bakkes_rcon-0.0.1.dist-info/METADATA
bakkes_rcon-0.0.1.dist-info/RECORD
